{
  "fires": [
    {
      "latitude": 37.91879,
      "longitude": 23.07355,
      "bright_ti4": 304.34,
      "scan": 0.48,
      "track": 0.4,
      "acq_date": "2026-06-01",
      "acq_time": 39,
      "satellite": "N20",
      "instrument": "VIIRS",
      "confidence": "n",
      "version": "2.0NRT",
      "bright_ti5": 293.19,
      "frp": 1.82,
      "daynight": "N",
      "data_source": "VIIRS_NOAA20_NRT",
      "region": "Greece",
      "id": "37.91879_23.07355_2026-06-01_39",
      "fetch_timestamp": "2026-06-01T08:26:06.802269+00:00",
      "api_method": "area_api_fallback"
    },
    {
      "latitude": 38.42752,
      "longitude": 27.21469,
      "bright_ti4": 303.32,
      "scan": 0.49,
      "track": 0.48,
      "acq_date": "2026-06-01",
      "acq_time": 39,
      "satellite": "N20",
      "instrument": "VIIRS",
      "confidence": "n",
      "version": "2.0NRT",
      "bright_ti5": 288.22,
      "frp": 0.7,
      "daynight": "N",
      "data_source": "VIIRS_NOAA20_NRT",
      "region": "Greece",
      "id": "38.42752_27.21469_2026-06-01_39",
      "fetch_timestamp": "2026-06-01T08:26:06.802290+00:00",
      "api_method": "area_api_fallback"
    },
    {
      "latitude": 38.73554,
      "longitude": 26.94955,
      "bright_ti4": 303.55,
      "scan": 0.46,
      "track": 0.47,
      "acq_date": "2026-06-01",
      "acq_time": 39,
      "satellite": "N20",
      "instrument": "VIIRS",
      "confidence": "n",
      "version": "2.0NRT",
      "bright_ti5": 289.34,
      "frp": 1.16,
      "daynight": "N",
      "data_source": "VIIRS_NOAA20_NRT",
      "region": "Greece",
      "id": "38.73554_26.94955_2026-06-01_39",
      "fetch_timestamp": "2026-06-01T08:26:06.802294+00:00",
      "api_method": "area_api_fallback"
    },
    {
      "latitude": 38.73672,
      "longitude": 26.94444,
      "bright_ti4": 306.31,
      "scan": 0.46,
      "track": 0.47,
      "acq_date": "2026-06-01",
      "acq_time": 39,
      "satellite": "N20",
      "instrument": "VIIRS",
      "confidence": "n",
      "version": "2.0NRT",
      "bright_ti5": 291.03,
      "frp": 1.91,
      "daynight": "N",
      "data_source": "VIIRS_NOAA20_NRT",
      "region": "Greece",
      "id": "38.73672_26.94444_2026-06-01_39",
      "fetch_timestamp": "2026-06-01T08:26:06.802298+00:00",
      "api_method": "area_api_fallback"
    },
    {
      "latitude": 38.73972,
      "longitude": 26.95123,
      "bright_ti4": 306.45,
      "scan": 0.46,
      "track": 0.47,
      "acq_date": "2026-06-01",
      "acq_time": 39,
      "satellite": "N20",
      "instrument": "VIIRS",
      "confidence": "n",
      "version": "2.0NRT",
      "bright_ti5": 288.43,
      "frp": 1.16,
      "daynight": "N",
      "data_source": "VIIRS_NOAA20_NRT",
      "region": "Greece",
      "id": "38.73972_26.95123_2026-06-01_39",
      "fetch_timestamp": "2026-06-01T08:26:06.802301+00:00",
      "api_method": "area_api_fallback"
    },
    {
      "latitude": 38.74092,
      "longitude": 26.94601,
      "bright_ti4": 318.63,
      "scan": 0.46,
      "track": 0.47,
      "acq_date": "2026-06-01",
      "acq_time": 39,
      "satellite": "N20",
      "instrument": "VIIRS",
      "confidence": "n",
      "version": "2.0NRT",
      "bright_ti5": 290.11,
      "frp": 1.91,
      "daynight": "N",
      "data_source": "VIIRS_NOAA20_NRT",
      "region": "Greece",
      "id": "38.74092_26.94601_2026-06-01_39",
      "fetch_timestamp": "2026-06-01T08:26:06.802304+00:00",
      "api_method": "area_api_fallback"
    },
    {
      "latitude": 38.74392,
      "longitude": 26.95285,
      "bright_ti4": 310.81,
      "scan": 0.46,
      "track": 0.47,
      "acq_date": "2026-06-01",
      "acq_time": 39,
      "satellite": "N20",
      "instrument": "VIIRS",
      "confidence": "n",
      "version": "2.0NRT",
      "bright_ti5": 289.0,
      "frp": 1.39,
      "daynight": "N",
      "data_source": "VIIRS_NOAA20_NRT",
      "region": "Greece",
      "id": "38.74392_26.95285_2026-06-01_39",
      "fetch_timestamp": "2026-06-01T08:26:06.802308+00:00",
      "api_method": "area_api_fallback"
    },
    {
      "latitude": 38.74513,
      "longitude": 26.94759,
      "bright_ti4": 305.02,
      "scan": 0.46,
      "track": 0.47,
      "acq_date": "2026-06-01",
      "acq_time": 39,
      "satellite": "N20",
      "instrument": "VIIRS",
      "confidence": "n",
      "version": "2.0NRT",
      "bright_ti5": 288.86,
      "frp": 1.26,
      "daynight": "N",
      "data_source": "VIIRS_NOAA20_NRT",
      "region": "Greece",
      "id": "38.74513_26.94759_2026-06-01_39",
      "fetch_timestamp": "2026-06-01T08:26:06.802311+00:00",
      "api_method": "area_api_fallback"
    },
    {
      "latitude": 38.75172,
      "longitude": 26.93882,
      "bright_ti4": 309.29,
      "scan": 0.46,
      "track": 0.47,
      "acq_date": "2026-06-01",
      "acq_time": 39,
      "satellite": "N20",
      "instrument": "VIIRS",
      "confidence": "n",
      "version": "2.0NRT",
      "bright_ti5": 288.76,
      "frp": 1.42,
      "daynight": "N",
      "data_source": "VIIRS_NOAA20_NRT",
      "region": "Greece",
      "id": "38.75172_26.93882_2026-06-01_39",
      "fetch_timestamp": "2026-06-01T08:26:06.802314+00:00",
      "api_method": "area_api_fallback"
    },
    {
      "latitude": 39.0924,
      "longitude": 27.51422,
      "bright_ti4": 301.53,
      "scan": 0.49,
      "track": 0.48,
      "acq_date": "2026-06-01",
      "acq_time": 39,
      "satellite": "N20",
      "instrument": "VIIRS",
      "confidence": "n",
      "version": "2.0NRT",
      "bright_ti5": 286.18,
      "frp": 0.91,
      "daynight": "N",
      "data_source": "VIIRS_NOAA20_NRT",
      "region": "Greece",
      "id": "39.0924_27.51422_2026-06-01_39",
      "fetch_timestamp": "2026-06-01T08:26:06.802317+00:00",
      "api_method": "area_api_fallback"
    },
    {
      "latitude": 39.86695,
      "longitude": 26.24734,
      "bright_ti4": 299.0,
      "scan": 0.41,
      "track": 0.45,
      "acq_date": "2026-06-01",
      "acq_time": 39,
      "satellite": "N20",
      "instrument": "VIIRS",
      "confidence": "n",
      "version": "2.0NRT",
      "bright_ti5": 288.28,
      "frp": 1.41,
      "daynight": "N",
      "data_source": "VIIRS_NOAA20_NRT",
      "region": "Greece",
      "id": "39.86695_26.24734_2026-06-01_39",
      "fetch_timestamp": "2026-06-01T08:26:06.802320+00:00",
      "api_method": "area_api_fallback"
    },
    {
      "latitude": 39.86797,
      "longitude": 26.24275,
      "bright_ti4": 301.67,
      "scan": 0.4,
      "track": 0.45,
      "acq_date": "2026-06-01",
      "acq_time": 39,
      "satellite": "N20",
      "instrument": "VIIRS",
      "confidence": "n",
      "version": "2.0NRT",
      "bright_ti5": 287.67,
      "frp": 1.44,
      "daynight": "N",
      "data_source": "VIIRS_NOAA20_NRT",
      "region": "Greece",
      "id": "39.86797_26.24275_2026-06-01_39",
      "fetch_timestamp": "2026-06-01T08:26:06.802323+00:00",
      "api_method": "area_api_fallback"
    },
    {
      "latitude": 40.4458,
      "longitude": 27.14094,
      "bright_ti4": 301.85,
      "scan": 0.43,
      "track": 0.46,
      "acq_date": "2026-06-01",
      "acq_time": 39,
      "satellite": "N20",
      "instrument": "VIIRS",
      "confidence": "n",
      "version": "2.0NRT",
      "bright_ti5": 288.2,
      "frp": 1.05,
      "daynight": "N",
      "data_source": "VIIRS_NOAA20_NRT",
      "region": "Greece",
      "id": "40.4458_27.14094_2026-06-01_39",
      "fetch_timestamp": "2026-06-01T08:26:06.802327+00:00",
      "api_method": "area_api_fallback"
    },
    {
      "latitude": 40.44691,
      "longitude": 27.13613,
      "bright_ti4": 300.07,
      "scan": 0.43,
      "track": 0.46,
      "acq_date": "2026-06-01",
      "acq_time": 39,
      "satellite": "N20",
      "instrument": "VIIRS",
      "confidence": "n",
      "version": "2.0NRT",
      "bright_ti5": 288.53,
      "frp": 0.98,
      "daynight": "N",
      "data_source": "VIIRS_NOAA20_NRT",
      "region": "Greece",
      "id": "40.44691_27.13613_2026-06-01_39",
      "fetch_timestamp": "2026-06-01T08:26:06.802330+00:00",
      "api_method": "area_api_fallback"
    },
    {
      "latitude": 40.44804,
      "longitude": 27.1312,
      "bright_ti4": 300.02,
      "scan": 0.43,
      "track": 0.46,
      "acq_date": "2026-06-01",
      "acq_time": 39,
      "satellite": "N20",
      "instrument": "VIIRS",
      "confidence": "n",
      "version": "2.0NRT",
      "bright_ti5": 287.96,
      "frp": 0.98,
      "daynight": "N",
      "data_source": "VIIRS_NOAA20_NRT",
      "region": "Greece",
      "id": "40.44804_27.1312_2026-06-01_39",
      "fetch_timestamp": "2026-06-01T08:26:06.802333+00:00",
      "api_method": "area_api_fallback"
    },
    {
      "latitude": 40.70102,
      "longitude": 22.95304,
      "bright_ti4": 301.18,
      "scan": 0.43,
      "track": 0.38,
      "acq_date": "2026-06-01",
      "acq_time": 39,
      "satellite": "N20",
      "instrument": "VIIRS",
      "confidence": "n",
      "version": "2.0NRT",
      "bright_ti5": 290.56,
      "frp": 0.74,
      "daynight": "N",
      "data_source": "VIIRS_NOAA20_NRT",
      "region": "Greece",
      "id": "40.70102_22.95304_2026-06-01_39",
      "fetch_timestamp": "2026-06-01T08:26:06.802336+00:00",
      "api_method": "area_api_fallback"
    },
    {
      "latitude": 41.50109,
      "longitude": 19.74624,
      "bright_ti4": 310.35,
      "scan": 0.38,
      "track": 0.36,
      "acq_date": "2026-06-01",
      "acq_time": 39,
      "satellite": "N20",
      "instrument": "VIIRS",
      "confidence": "n",
      "version": "2.0NRT",
      "bright_ti5": 288.76,
      "frp": 1.12,
      "daynight": "N",
      "data_source": "VIIRS_NOAA20_NRT",
      "region": "Greece",
      "id": "41.50109_19.74624_2026-06-01_39",
      "fetch_timestamp": "2026-06-01T08:26:06.802340+00:00",
      "api_method": "area_api_fallback"
    },
    {
      "latitude": 41.71102,
      "longitude": 21.50682,
      "bright_ti4": 297.3,
      "scan": 0.39,
      "track": 0.37,
      "acq_date": "2026-06-01",
      "acq_time": 39,
      "satellite": "N20",
      "instrument": "VIIRS",
      "confidence": "n",
      "version": "2.0NRT",
      "bright_ti5": 281.54,
      "frp": 0.29,
      "daynight": "N",
      "data_source": "VIIRS_NOAA20_NRT",
      "region": "Greece",
      "id": "41.71102_21.50682_2026-06-01_39",
      "fetch_timestamp": "2026-06-01T08:26:06.802343+00:00",
      "api_method": "area_api_fallback"
    },
    {
      "latitude": 40.69694,
      "longitude": 22.95146,
      "bright_ti4": 298.97,
      "scan": 0.57,
      "track": 0.69,
      "acq_date": "2026-06-01",
      "acq_time": 128,
      "satellite": "N21",
      "instrument": "VIIRS",
      "confidence": "n",
      "version": "2.0NRT",
      "bright_ti5": 287.06,
      "frp": 1.4,
      "daynight": "N",
      "data_source": "VIIRS_NOAA21_NRT",
      "region": "Greece",
      "id": "40.69694_22.95146_2026-06-01_128",
      "fetch_timestamp": "2026-06-01T08:26:07.093204+00:00",
      "api_method": "area_api_fallback"
    },
    {
      "latitude": 41.5006,
      "longitude": 19.74196,
      "bright_ti4": 307.64,
      "scan": 0.37,
      "track": 0.58,
      "acq_date": "2026-06-01",
      "acq_time": 128,
      "satellite": "N21",
      "instrument": "VIIRS",
      "confidence": "n",
      "version": "2.0NRT",
      "bright_ti5": 287.43,
      "frp": 1.39,
      "daynight": "N",
      "data_source": "VIIRS_NOAA21_NRT",
      "region": "Greece",
      "id": "41.5006_19.74196_2026-06-01_128",
      "fetch_timestamp": "2026-06-01T08:26:07.093218+00:00",
      "api_method": "area_api_fallback"
    },
    {
      "latitude": 41.5013,
      "longitude": 19.74325,
      "bright_ti4": 311.52,
      "scan": 0.37,
      "track": 0.58,
      "acq_date": "2026-06-01",
      "acq_time": 128,
      "satellite": "N21",
      "instrument": "VIIRS",
      "confidence": "n",
      "version": "2.0NRT",
      "bright_ti5": 287.98,
      "frp": 1.45,
      "daynight": "N",
      "data_source": "VIIRS_NOAA21_NRT",
      "region": "Greece",
      "id": "41.5013_19.74325_2026-06-01_128",
      "fetch_timestamp": "2026-06-01T08:26:07.093223+00:00",
      "api_method": "area_api_fallback"
    },
    {
      "latitude": 41.54559,
      "longitude": 19.72398,
      "bright_ti4": 298.29,
      "scan": 0.37,
      "track": 0.58,
      "acq_date": "2026-06-01",
      "acq_time": 128,
      "satellite": "N21",
      "instrument": "VIIRS",
      "confidence": "n",
      "version": "2.0NRT",
      "bright_ti5": 286.85,
      "frp": 0.6,
      "daynight": "N",
      "data_source": "VIIRS_NOAA21_NRT",
      "region": "Greece",
      "id": "41.54559_19.72398_2026-06-01_128",
      "fetch_timestamp": "2026-06-01T08:26:07.093226+00:00",
      "api_method": "area_api_fallback"
    }
  ],
  "count": 22,
  "dataset": "live",
  "last_updated": "2026-06-01T08:26:07.240222+00:00",
  "sources": [
    "MODIS_NRT",
    "VIIRS_SNPP_NRT",
    "VIIRS_NOAA20_NRT",
    "VIIRS_NOAA21_NRT"
  ],
  "geographic_bounds": {
    "north": 41.75,
    "south": 34.5,
    "east": 34.8,
    "west": 19.5
  },
  "using_fallback_data": false
}